allotools/__init__.py
allotools/allo_use_plot.py
allotools/allocation_ts.py
allotools/core.py
allotools/filters.py
allotools/parameters.py
allotools/plot.py
allotools/util.py
allotools/tests/__init__.py
allotools/tests/t_AlloUsage_alt1.py
allotools/tests/t_AlloUsage_alt2.py
allotools/tests/test_AlloUsage.py
EcanAlloUsageTools-0.2.8.dist-info/LICENSE.txt
EcanAlloUsageTools-0.2.8.dist-info/METADATA
EcanAlloUsageTools-0.2.8.dist-info/WHEEL
EcanAlloUsageTools-0.2.8.dist-info/top_level.txt
EcanAlloUsageTools-0.2.8.dist-info/RECORD
