Metadata-Version: 2.1
Name: EcanAlloUsageTools
Version: 0.2.8
Summary: Functions to process and analyse ECan allocation and usage data
Home-page: https://github.com/mullenkamp/EcanAlloUsageTools
Author: Mike Kittridge
Author-email: mullenkamp1@gmail.com
License: Apache
Keywords: allocation
Platform: UNKNOWN
Classifier: Development Status :: 3 - Alpha
Classifier: Intended Audience :: Developers
Classifier: Topic :: Software Development :: Build Tools
Classifier: License :: OSI Approved :: Apache Software License
Classifier: Programming Language :: Python :: 2
Classifier: Programming Language :: Python :: 2.7
Classifier: Programming Language :: Python :: 3
Classifier: Programming Language :: Python :: 3.4
Classifier: Programming Language :: Python :: 3.5
Classifier: Programming Language :: Python :: 3.6
Requires-Dist: pandas
Requires-Dist: pdsql
Requires-Dist: seaborn
